orchd_sdk/VERSION
orchd_sdk/__init__.py
orchd_sdk/cli.py
orchd_sdk/common.py
orchd_sdk/errors.py
orchd_sdk/logger.ini
orchd_sdk/logging.py
orchd_sdk/models.py
orchd_sdk/project.py
orchd_sdk/reaction.py
orchd_sdk/sensor.py
orchd_sdk/sink.py
orchd_sdk/util.py
orchd_sdk/api/__init__.py
orchd_sdk/api/events.py
orchd_sdk/api/reactions.py
orchd_sdk/api/sensors.py
orchd_sdk/api/sinks.py
orchd_sdk-0.1a9.dist-info/LICENSE.md
orchd_sdk-0.1a9.dist-info/METADATA
orchd_sdk-0.1a9.dist-info/WHEEL
orchd_sdk-0.1a9.dist-info/entry_points.txt
orchd_sdk-0.1a9.dist-info/top_level.txt
orchd_sdk-0.1a9.dist-info/RECORD
