Metadata-Version: 2.1
Name: orchd-sdk
Version: 0.1a9
Summary: SDK for Orchd Ecosystem Applications
Home-page: http://orchd.io
Author: Mathias Santos de Brito
Author-email: mathias.brito@me.com
License: UNKNOWN
Keywords: service resource orchestration edge cloud
Platform: UNKNOWN
Classifier: License :: Other/Proprietary License
Classifier: Intended Audience :: Information Technology
Classifier: Operating System :: POSIX
Classifier: Programming Language :: Python :: 3.8
Classifier: Programming Language :: Python :: 3.9
Classifier: Programming Language :: Python :: 3.10
Classifier: Topic :: System :: Distributed Computing
Requires-Dist: click
Requires-Dist: reactivex
Requires-Dist: pydantic
Requires-Dist: GitPython
Requires-Dist: colorama
Provides-Extra: docs
Requires-Dist: sphinx ; extra == 'docs'
Requires-Dist: sphinx-rtd-theme ; extra == 'docs'
Provides-Extra: test
Requires-Dist: click ; extra == 'test'
Requires-Dist: reactivex ; extra == 'test'
Requires-Dist: pydantic ; extra == 'test'
Requires-Dist: GitPython ; extra == 'test'
Requires-Dist: colorama ; extra == 'test'
Requires-Dist: pytest ; extra == 'test'
Requires-Dist: pytest-asyncio ; extra == 'test'
Requires-Dist: coverage ; extra == 'test'
Requires-Dist: black ; extra == 'test'
Requires-Dist: mypy ; extra == 'test'
